NwjsDoc/README.md
NwjsDoc/__init__.py
NwjsDoc/__main__.py
NwjsDoc/file.epub
NwjsDoc/index.html
NwjsDoc/css/__init__.py
NwjsDoc/css/annotations.css
NwjsDoc/css/main.css
NwjsDoc/css/normalize.css
NwjsDoc/css/popup.css
NwjsDoc/font/__init__.py
NwjsDoc/font/fontello.eot
NwjsDoc/font/fontello.svg
NwjsDoc/font/fontello.ttf
NwjsDoc/font/fontello.woff
NwjsDoc/img/__init__.py
NwjsDoc/img/annotator-glyph-sprite.png
NwjsDoc/img/annotator-icon-sprite.png
NwjsDoc/img/apple-touch-icon.png
NwjsDoc/img/cancelfullscreen.png
NwjsDoc/img/close.png
NwjsDoc/img/fullscreen.png
NwjsDoc/img/loader.gif
NwjsDoc/img/menu-icon.png
NwjsDoc/img/save.png
NwjsDoc/img/saved.png
NwjsDoc/img/settings-s.png
NwjsDoc/img/settings.png
NwjsDoc/img/star.png
NwjsDoc/js/__init__.py
NwjsDoc/js/epub.js
NwjsDoc/js/epub.min.js
NwjsDoc/js/epub.min.map
NwjsDoc/js/hooks.min.js
NwjsDoc/js/hooks.min.map
NwjsDoc/js/reader.js
NwjsDoc/js/reader.js.map
NwjsDoc/js/reader.min.js
NwjsDoc/js/reader.min.map
NwjsDoc/js/hooks/__init__.py
NwjsDoc/js/hooks/extensions/__init__.py
NwjsDoc/js/hooks/extensions/highlight.js
NwjsDoc/js/libs/__init__.py
NwjsDoc/js/libs/jquery.min.js
NwjsDoc/js/libs/localforage.min.js
NwjsDoc/js/libs/screenfull.js
NwjsDoc/js/libs/screenfull.min.js
NwjsDoc/js/libs/zip.min.js
NwjsDoc/js/plugins/__init__.py
NwjsDoc/js/plugins/hypothesis.js
NwjsDoc/js/plugins/search.js
nwjs_doc-2024.3.1.0.dist-info/METADATA
nwjs_doc-2024.3.1.0.dist-info/WHEEL
nwjs_doc-2024.3.1.0.dist-info/entry_points.txt
nwjs_doc-2024.3.1.0.dist-info/top_level.txt
nwjs_doc-2024.3.1.0.dist-info/RECORD
